[
  {
    "id": "evt-sports-001",
    "title": "Intercollege Football Tournament",
    "category": "sports",
    "description": "Join the thrilling battle of goals and glory! Teams from across the region will compete for the grand trophy.",
    "date": "2026-04-10",
    "time": "10:00",
    "venue": "Main Ground",
    "image": "https://placehold.co/400x250/87CEEB/ffffff?text=Football+Tournament",
    "price": 150,
    "createdAt": "2026-03-11T08:00:00.000Z"
  },
  {
    "id": "evt-sports-002",
    "title": "Annual Basketball League",
    "category": "sports",
    "description": "Experience fast-paced action and skill as college teams face off in this high-energy basketball league.",
    "date": "2026-04-15",
    "time": "14:00",
    "venue": "Indoor Stadium",
    "image": "https://placehold.co/400x250/6495ED/ffffff?text=Basketball+League",
    "createdAt": "2026-03-11T08:00:00.000Z"
  },
  {
    "id": "evt-sports-003",
    "title": "Cricket Carnival",
    "category": "sports",
    "description": "The most awaited cricket match of the year — where sixes, cheers, and rivalry fill the air.",
    "date": "2026-04-20",
    "time": "09:00",
    "venue": "Cricket Ground",
    "image": "https://placehold.co/400x250/00BFFF/ffffff?text=Cricket+Match",
    "price": 100,
    "createdAt": "2026-03-11T08:00:00.000Z"
  },
  {
    "id": "evt-sports-004",
    "title": "Annual Athletics Meet",
    "category": "sports",
    "description": "Show your strength, stamina, and speed across multiple track and field events.",
    "date": "2026-04-25",
    "time": "08:00",
    "venue": "Athletics Track",
    "image": "https://placehold.co/400x250/1E90FF/ffffff?text=Athletics+Meet",
    "createdAt": "2026-03-11T08:00:00.000Z"
  },
  {
    "id": "evt-sports-005",
    "title": "Table Tennis Showdown",
    "category": "sports",
    "description": "A fast-paced table tennis tournament to test your reflexes and focus.",
    "date": "2026-05-01",
    "time": "11:00",
    "venue": "Sports Hall",
    "image": "https://placehold.co/400x250/4682B4/ffffff?text=Table+Tennis",
    "price": 50,
    "createdAt": "2026-03-11T08:00:00.000Z"
  },
  {
    "id": "evt-comedy-001",
    "title": "Campus Stand-Up Night",
    "category": "comedy",
    "description": "Laugh out loud as budding comedians take the stage with hilarious sets.",
    "date": "2026-04-12",
    "time": "19:00",
    "venue": "Auditorium",
    "image": "https://placehold.co/400x250/FFA07A/ffffff?text=Stand-Up+Night",
    "price": 200,
    "createdAt": "2026-03-11T08:00:00.000Z"
  },
  {
    "id": "evt-comedy-002",
    "title": "Mimicry Madness",
    "category": "comedy",
    "description": "Impersonations, jokes, and laughter guaranteed — can you guess who's who?",
    "date": "2026-04-18",
    "time": "18:00",
    "venue": "Open Air Theatre",
    "image": "https://placehold.co/400x250/FF7F50/ffffff?text=Mimicry+Show",
    "createdAt": "2026-03-11T08:00:00.000Z"
  },
  {
    "id": "evt-comedy-003",
    "title": "Funny Skit Competition",
    "category": "comedy",
    "description": "Teams perform short comic plays that'll have you in splits.",
    "date": "2026-04-22",
    "time": "17:00",
    "venue": "Main Hall",
    "image": "https://placehold.co/400x250/FF6347/ffffff?text=Funny+Skit",
    "price": 80,
    "createdAt": "2026-03-11T08:00:00.000Z"
  },
  {
    "id": "evt-comedy-004",
    "title": "Comedy Battle",
    "category": "comedy",
    "description": "The ultimate face-off between the funniest minds on campus.",
    "date": "2026-04-28",
    "time": "20:00",
    "venue": "Auditorium",
    "image": "https://placehold.co/400x250/FF4500/ffffff?text=Comedy+Battle",
    "createdAt": "2026-03-11T08:00:00.000Z"
  },
  {
    "id": "evt-comedy-005",
    "title": "Improv Night",
    "category": "comedy",
    "description": "Unscripted humor at its best — watch comedians create scenes on the spot.",
    "date": "2026-05-05",
    "time": "19:30",
    "venue": "Black Box Theatre",
    "image": "https://placehold.co/400x250/DC143C/ffffff?text=Improv+Night",
    "createdAt": "2026-03-11T08:00:00.000Z"
  },
  {
    "id": "evt-theatre-001",
    "title": "Classic Stage Drama",
    "category": "theatre",
    "description": "Experience a powerful theatrical performance that blends art and storytelling.",
    "date": "2026-04-14",
    "time": "18:30",
    "venue": "Main Auditorium",
    "image": "https://placehold.co/400x250/90EE90/ffffff?text=Stage+Play",
    "price": 120,
    "createdAt": "2026-03-11T08:00:00.000Z"
  },
  {
    "id": "evt-theatre-002",
    "title": "Mono Act Challenge",
    "category": "theatre",
    "description": "Watch performers captivate the audience with solo acting brilliance.",
    "date": "2026-04-19",
    "time": "17:00",
    "venue": "Studio Theatre",
    "image": "https://placehold.co/400x250/3CB371/ffffff?text=Mono+Act",
    "createdAt": "2026-03-11T08:00:00.000Z"
  },
  {
    "id": "evt-theatre-003",
    "title": "Nukkad Natak",
    "category": "theatre",
    "description": "An open-air street performance spreading social awareness through theatre.",
    "date": "2026-04-24",
    "time": "16:00",
    "venue": "College Lawns",
    "image": "https://placehold.co/400x250/2E8B57/ffffff?text=Street+Play",
    "createdAt": "2026-03-11T08:00:00.000Z"
  },
  {
    "id": "evt-theatre-004",
    "title": "Intercollege Drama Fest",
    "category": "theatre",
    "description": "Teams compete with thought-provoking dramas and stage plays.",
    "date": "2026-05-02",
    "time": "11:00",
    "venue": "Main Auditorium",
    "image": "https://placehold.co/400x250/228B22/ffffff?text=Drama+Festival",
    "price": 180,
    "createdAt": "2026-03-11T08:00:00.000Z"
  },
  {
    "id": "evt-theatre-005",
    "title": "Mime Magic",
    "category": "theatre",
    "description": "A silent performance that speaks volumes through expressions and gestures.",
    "date": "2026-05-08",
    "time": "17:30",
    "venue": "Open Stage",
    "image": "https://placehold.co/400x250/006400/ffffff?text=Mime+Act",
    "createdAt": "2026-03-11T08:00:00.000Z"
  },
  {
    "id": "evt-movies-001",
    "title": "Open-Air Movie Night",
    "category": "movies",
    "description": "Enjoy a blockbuster under the stars with popcorn and friends.",
    "date": "2026-04-11",
    "time": "20:00",
    "venue": "College Lawns",
    "image": "https://placehold.co/400x250/FF69B4/ffffff?text=Movie+Night",
    "price": 100,
    "createdAt": "2026-03-11T08:00:00.000Z"
  },
  {
    "id": "evt-movies-002",
    "title": "Short Film Showcase",
    "category": "movies",
    "description": "Watch creative short films by talented student filmmakers.",
    "date": "2026-04-17",
    "time": "15:00",
    "venue": "Screening Room",
    "image": "https://placehold.co/400x250/FF1493/ffffff?text=Short+Film",
    "createdAt": "2026-03-11T08:00:00.000Z"
  },
  {
    "id": "evt-movies-003",
    "title": "Film Trivia Night",
    "category": "movies",
    "description": "Test your cinema knowledge in a fun quiz about classics and blockbusters.",
    "date": "2026-04-23",
    "time": "19:00",
    "venue": "Seminar Hall",
    "image": "https://placehold.co/400x250/DB7093/ffffff?text=Film+Quiz",
    "createdAt": "2026-03-11T08:00:00.000Z"
  },
  {
    "id": "evt-movies-004",
    "title": "Director's Talk",
    "category": "movies",
    "description": "Meet local filmmakers and learn the craft behind the camera.",
    "date": "2026-04-29",
    "time": "14:00",
    "venue": "Conference Room",
    "image": "https://placehold.co/400x250/C71585/ffffff?text=Directors+Talk",
    "createdAt": "2026-03-11T08:00:00.000Z"
  },
  {
    "id": "evt-movies-005",
    "title": "Animation Fest",
    "category": "movies",
    "description": "Explore student-made animations and visual storytelling art.",
    "date": "2026-05-06",
    "time": "13:00",
    "venue": "Media Lab",
    "image": "https://placehold.co/400x250/FFB6C1/ffffff?text=Animation+Fest",
    "price": 60,
    "createdAt": "2026-03-11T08:00:00.000Z"
  },
  {
    "id": "evt-concerts-001",
    "title": "Rock Night",
    "category": "concerts",
    "description": "Feel the energy as live bands set the stage on fire!",
    "date": "2026-04-13",
    "time": "20:00",
    "venue": "Open Amphitheatre",
    "image": "https://placehold.co/400x250/8A2BE2/ffffff?text=Rock+Concert",
    "price": 300,
    "createdAt": "2026-03-11T08:00:00.000Z"
  },
  {
    "id": "evt-concerts-002",
    "title": "EDM Party",
    "category": "concerts",
    "description": "Dance to electrifying beats with DJ sets lighting up the night.",
    "date": "2026-04-19",
    "time": "21:00",
    "venue": "College Grounds",
    "image": "https://placehold.co/400x250/9370DB/ffffff?text=EDM+Party",
    "price": 250,
    "createdAt": "2026-03-11T08:00:00.000Z"
  },
  {
    "id": "evt-concerts-003",
    "title": "Acoustic Evening",
    "category": "concerts",
    "description": "Relax and unwind with soulful acoustic tunes.",
    "date": "2026-04-26",
    "time": "18:00",
    "venue": "Garden Area",
    "image": "https://placehold.co/400x250/BA55D3/ffffff?text=Acoustic+Evening",
    "createdAt": "2026-03-11T08:00:00.000Z"
  },
  {
    "id": "evt-concerts-004",
    "title": "Battle of the Bands",
    "category": "concerts",
    "description": "Student bands compete for the title of campus rockstar.",
    "date": "2026-05-03",
    "time": "19:00",
    "venue": "Main Stage",
    "image": "https://placehold.co/400x250/9932CC/ffffff?text=Battle+of+Bands",
    "price": 150,
    "createdAt": "2026-03-11T08:00:00.000Z"
  },
  {
    "id": "evt-concerts-005",
    "title": "Fusion Night",
    "category": "concerts",
    "description": "A blend of classical and modern music — one mesmerizing evening!",
    "date": "2026-05-10",
    "time": "19:30",
    "venue": "Auditorium",
    "image": "https://placehold.co/400x250/9400D3/ffffff?text=Fusion+Night",
    "createdAt": "2026-03-11T08:00:00.000Z"
  },
  {
    "id": "4d93e301-3481-4a03-8aca-5eda874365fd",
    "title": "Music Night",
    "category": "concerts",
    "description": "Music night with full of fun.",
    "date": "2026-03-15",
    "time": "6:00",
    "venue": "Alpha Zone",
    "image": "https://placehold.co/400x250/cccccc/ffffff?text=Music%20Night",
    "createdAt": "2026-03-12T04:02:23.050Z"
  }
]